aiotelebotuz/__init__.py
aiotelebotuz/bot.py
aiotelebotuz/holat.py
aiotelebotuz/media.py
aiotelebotuz/tugmalar.py
aiotelebotuz-1.0.0.dist-info/licenses/LICENSE
aiotelebotuz-1.0.0.dist-info/METADATA
aiotelebotuz-1.0.0.dist-info/WHEEL
aiotelebotuz-1.0.0.dist-info/top_level.txt
aiotelebotuz-1.0.0.dist-info/RECORD
