Metadata-Version: 2.4
Name: aiotelebotuz
Version: 1.0.0
Summary: Aiogram 3 uchun o'zbekcha va juda oson kutubxona
Home-page: https://github.com/sizning-username/aiotelebot
Author: AioTeleBot
Author-email: SIZNING_ISMINGIZ <sizning@email.com>
License: MIT
Project-URL: Homepage, https://github.com/SIZNING_USERNAME/aiotelebot
Project-URL: Documentation, https://github.com/SIZNING_USERNAME/aiotelebot#readme
Project-URL: Repository, https://github.com/SIZNING_USERNAME/aiotelebot
Project-URL: Issues, https://github.com/SIZNING_USERNAME/aiotelebot/issues
Keywords: telegram,bot,aiogram,uzbek,o'zbek,oson
Classifier: Development Status :: 4 - Beta
Classifier: Intended Audience :: Developers
Classifier: License :: OSI Approved :: MIT License
Classifier: Programming Language :: Python :: 3
Classifier: Programming Language :: Python :: 3.8
Classifier: Programming Language :: Python :: 3.9
Classifier: Programming Language :: Python :: 3.10
Classifier: Programming Language :: Python :: 3.11
Classifier: Programming Language :: Python :: 3.12
Classifier: Framework :: AsyncIO
Classifier: Topic :: Software Development :: Libraries :: Python Modules
Requires-Python: >=3.8
License-File: LICENSE
Requires-Dist: aiogram>=3.0.0
Requires-Dist: aiohttp>=3.8.0
Dynamic: author
Dynamic: home-page
Dynamic: license-file
Dynamic: requires-python
